{
  "job": {
    "title": "Machine Learning Engineer",
    "industry": "",
    "description": "",
    "employment_type": "CONTRACTOR",
    "date_posted": "2021-08-06T22:14:28.000Z"
  },
  "company": {
    "name": "Harvey Nash",
    "link": "https://uk.linkedin.com/company/harvey-nash"
  },
  "education": {
    "required_credential": "bachelor degree"
  },
  "experience": {
    "months_of_experience": 72,
    "seniority_level": " "
  },
  "salary": {
    "currency": " ",
    "min_value": 0,
    "max_value": 0,
    "unit": " "
  },
  "location": {
    "country": "US",
    "locality": "Pleasanton",
    "region": "CA",
    "postal_code": "94588",
    "street_address": null,
    "latitude": 37.658436,
    "longitude": -121.877
  }
}