{
  "job": {
    "title": "Senior Software Engineer (.NET)",
    "industry": "Accounting,Financial Services,Information Technology and Services",
    "description": "$115.000 - $125,000",
    "employment_type": "FULL_TIME",
    "date_posted": "2021-08-24T01:11:36.000Z"
  },
  "company": {
    "name": "Allied OneSource",
    "link": "https://www.linkedin.com/company/allied-onesource"
  },
  "education": {
    "required_credential": "bachelor degree"
  },
  "experience": {
    "months_of_experience": 60,
    "seniority_level": " "
  },
  "salary": {
    "currency": "USD",
    "min_value": 81400,
    "max_value": 138000,
    "unit": "YEAR"
  },
  "location": {
    "country": "US",
    "locality": "West Des Moines",
    "region": "IA",
    "postal_code": "50265",
    "street_address": null,
    "latitude": 41.575504,
    "longitude": -93.71303
  }
}